tests/__init__.py
tests/conftest.py
tests/test_cli.py
tests/test_muffin.py
tests/test_utils.py
tests/test_xsession.py
tests/test_xsessionp.py
tests/testutils.py
xsessionp/__init__.py
xsessionp/cli.py
xsessionp/ewmh.py
xsessionp/icccm.py
xsessionp/muffin.py
xsessionp/utils.py
xsessionp/xsession.py
xsessionp/xsessionp.py
xsessionp-0.1.4.dist-info/LICENSE.md
xsessionp-0.1.4.dist-info/METADATA
xsessionp-0.1.4.dist-info/WHEEL
xsessionp-0.1.4.dist-info/entry_points.txt
xsessionp-0.1.4.dist-info/top_level.txt
xsessionp-0.1.4.dist-info/RECORD
