Metadata-Version: 2.1
Name: xsessionp
Version: 0.1.4
Summary: A declarative window instantiation utility for x11 sessions, heavily inspired by tmuxp.
Home-page: https://pypi.org/project/xsessionp/
Author: Richard Davis
Author-email: crashvb@gmail.com
License: Apache License 2.0
Project-URL: Bug Reports, https://github.com/crashvb/xsessionp/issues
Project-URL: Source, https://github.com/crashvb/xsessionp
Keywords: instantiation sessions window x11 xsession xsessionp xsp
Platform: UNKNOWN
Classifier: Development Status :: 4 - Beta
Classifier: Intended Audience :: End Users/Desktop
Classifier: License :: OSI Approved :: Apache Software License
Classifier: Programming Language :: Python :: 3
Classifier: Programming Language :: Python :: 3.8
Classifier: Programming Language :: Python :: 3.9
Classifier: Programming Language :: Python :: 3.10
Classifier: Operating System :: POSIX :: Linux
Requires-Dist: click
Requires-Dist: flatten-dict
Requires-Dist: python-xlib
Requires-Dist: pyyaml
Provides-Extra: dev
Requires-Dist: black ; extra == 'dev'
Requires-Dist: coveralls ; extra == 'dev'
Requires-Dist: pylint ; extra == 'dev'
Requires-Dist: pytest ; extra == 'dev'
Requires-Dist: pytest-cov ; extra == 'dev'
Requires-Dist: python-xlib ; extra == 'dev'
Requires-Dist: twine ; extra == 'dev'
Requires-Dist: wheel ; extra == 'dev'
